{
  "models": [
    {
      "id": "gigaam-v3-ru-quality",
      "displayName": "GigaAM v3",
      "description": "Качественная русская ASR-модель GigaAM v3.",
      "type": "asr",
      "engine": "gigaam-v3",
      "language": "ru",
      "version": "v3",
      "sizeMb": null,
      "requiresDiarization": false,
      "download": {
        "url": "https://cdn.chatwm.opensmodel.sberdevices.ru/GigaAM/v3_e2e_rnnt.ckpt",
        "segmentationUrl": null,
        "embeddingUrl": "https://cdn.chatwm.opensmodel.sberdevices.ru/GigaAM/v3_e2e_rnnt_tokenizer.model",
        "archiveType": null,
        "sha256": null
      },
      "install": {
        "targetFolder": "gigaam-v3-ru-quality",
        "requiredFiles": [
          "v3_e2e_rnnt.ckpt",
          "v3_e2e_rnnt_tokenizer.model"
        ]
      },
      "runtime": {
        "sampleRate": 16000,
        "channels": 1,
        "device": "cpu"
      }
    },
    {
      "id": "pyannote-community-1",
      "displayName": "Спикеры — Pyannote Community-1",
      "description": "Локальная диаризация через Pyannote Community-1. Требует принятия условий модели и Hugging Face access token только для скачивания.",
      "type": "diarization",
      "engine": "pyannote-community-1",
      "language": "any",
      "version": "community-1",
      "sizeMb": 34,
      "requiresDiarization": false,
      "download": {
        "url": null,
        "segmentationUrl": null,
        "embeddingUrl": null,
        "huggingFaceRepoId": "pyannote/speaker-diarization-community-1",
        "huggingFaceRevision": "main",
        "requiresAuthorization": true,
        "archiveType": null,
        "sha256": null
      },
      "install": {
        "targetFolder": "pyannote-community-1",
        "requiredFiles": [
          "config.yaml",
          "segmentation/pytorch_model.bin",
          "embedding/pytorch_model.bin",
          "plda/plda.npz",
          "plda/xvec_transform.npz"
        ]
      },
      "runtime": {
        "sampleRate": 16000,
        "channels": 1,
        "device": "cpu"
      }
    }
  ]
}
